RoughSets.py
__init__.py
example.py
roughsetkr-0.0.1.dist-info/METADATA
roughsetkr-0.0.1.dist-info/WHEEL
roughsetkr-0.0.1.dist-info/licenses/LICENSE
roughsetkr-0.0.1.dist-info/RECORD
