Metadata-Version: 2.1
Name: RoughSetKR
Version: 0.0.1
Summary: This is a python package that uses the rough set algorithm to measure which features can be reduced.
Project-URL: Homepage, https://github.com/YiyaoZhang9527/Algorithm-class-at-Huai-Vocational-College
Author-email: ManmanZhang <408903228@qq.com>
License: MIT License
License-File: LICENSE
Classifier: License :: OSI Approved :: MIT License
Classifier: Operating System :: OS Independent
Classifier: Programming Language :: Python :: 3
Requires-Python: >=3.7
Requires-Dist: numpy>=1.21.6
Requires-Dist: pandas>=1.3.5
